[{"id":"1","name":"Masami Kurumada","site":""},{"id":"2","name":"Megumu Okada","site":""},{"id":"3","name":"Shiori Teshirogi","site":"https://twitter.com/teshi_kuro413"},{"id":"4","name":"Chimaki Kuori","site":"https://twitter.com/cmk_k"},{"id":"5","name":"Marco Albiero","site":"https://www.instagram.com/marcoalbieroart/"},{"id":"6","name":"Márcio Damassena (Cerberus Rack)","site":"https://www.deviantart.com/cerberus-rack"},{"id":"7","name":"Trident Poseidon","site":""},{"id":"8","name":"Libra no Genbu","site":"https://www.instagram.com/loic.penet/"},{"id":"9","name":"Juan Manuel Granados Sandoval (Manik)","site":"https://www.instagram.com/manik_ocelot/"},{"id":"10","name":"LadyHeinstein","site":"https://www.instagram.com/ladyheinstein/"},{"id":"11","name":"markolios","site":""},{"id":"12","name":"","site":""},{"id":"13","name":"","site":""},{"id":"14","name":"Felipe Marchioni","site":"https://www.instagram.com/mikhairon/"},{"id":"15","name":"Dannilo Sant'anna de Quadros","site":"https://www.facebook.com/dannilosantannadequadros"},{"id":"16","name":"Lui Rayson","site":"https://www.instagram.com/lui_rayson/"},{"id":"17","name":"Emi MMXIII","site":""},{"id":"18","name":"Srw13","site":"https://www.deviantart.com/srw13"},{"id":"19","name":"ABottle","site":"https://www.pharaonwebsite.com/users/abottle/fanarts/"}]