[{"id":"1","group":"eris-gods","class":"Dryads","classSingular":"Dryad","name":"Gods"},{"id":"1","group":"eris-phantoms","class":"Dryads","classSingular":"Phantom","name":"Phantoms"},{"id":"1","group":"eris-ghost-saints","class":"Dryads","classSingular":"Ghost Five","name":"Ghost Five"},{"id":"2","group":"eris-ghost-saints","class":"Dryads","classSingular":"Ghost Saint","name":"Ghost Saints"},{"id":"1","group":"eris-dryads","class":"Dryads","classSingular":"Dryad","name":"Dryads"},{"id":"1","group":"eris-soldiers","class":"Dryads","classSingular":"Dryad Soldier","name":"Dryad Soldiers"}]